{
    "filename": "504_721851.jpg",
    "objects": [
        {
            "label": "snacks",
            "score": 0.5561585426330566,
            "box": [
                418,
                65,
                471,
                116
            ]
        },
        {
            "label": "snacks",
            "score": 0.4691554307937622,
            "box": [
                227,
                110,
                275,
                162
            ]
        },
        {
            "label": "snacks",
            "score": 0.46198752522468567,
            "box": [
                331,
                83,
                391,
                148
            ]
        },
        {
            "label": "snacks",
            "score": 0.4330222010612488,
            "box": [
                108,
                94,
                182,
                158
            ]
        },
        {
            "label": "snacks",
            "score": 0.3268083333969116,
            "box": [
                269,
                320,
                413,
                479
            ]
        },
        {
            "label": "snacks",
            "score": 0.35220175981521606,
            "box": [
                283,
                362,
                370,
                428
            ]
        }
    ]
}