{
    "filename": "590_805271.jpg",
    "objects": [
        {
            "label": "plant",
            "score": 0.601593554019928,
            "box": [
                233,
                0,
                293,
                123
            ]
        },
        {
            "label": "chair",
            "score": 0.5874698758125305,
            "box": [
                425,
                0,
                508,
                128
            ]
        },
        {
            "label": "chair",
            "score": 0.5384978652000427,
            "box": [
                119,
                0,
                224,
                153
            ]
        },
        {
            "label": "plant",
            "score": 0.48169761896133423,
            "box": [
                311,
                65,
                362,
                115
            ]
        },
        {
            "label": "cup",
            "score": 0.5360700488090515,
            "box": [
                395,
                338,
                445,
                416
            ]
        },
        {
            "label": "chair",
            "score": 0.5556763410568237,
            "box": [
                456,
                107,
                587,
                251
            ]
        },
        {
            "label": "plant",
            "score": 0.3225259780883789,
            "box": [
                343,
                71,
                361,
                114
            ]
        },
        {
            "label": "bottle",
            "score": 0.4527778625488281,
            "box": [
                435,
                275,
                469,
                323
            ]
        },
        {
            "label": "table",
            "score": 0.637030839920044,
            "box": [
                124,
                0,
                544,
                479
            ]
        },
        {
            "label": "plant",
            "score": 0.33111974596977234,
            "box": [
                312,
                66,
                332,
                114
            ]
        },
        {
            "label": "bag",
            "score": 0.3747906982898712,
            "box": [
                192,
                98,
                404,
                365
            ]
        },
        {
            "label": "chair",
            "score": 0.40450742840766907,
            "box": [
                41,
                121,
                193,
                257
            ]
        },
        {
            "label": "bottle",
            "score": 0.29421496391296387,
            "box": [
                421,
                275,
                469,
                345
            ]
        },
        {
            "label": "chair",
            "score": 0.29992473125457764,
            "box": [
                40,
                120,
                193,
                309
            ]
        }
    ]
}