{
    "filename": "722_894695.jpg",
    "objects": [
        {
            "label": "cup",
            "score": 0.7994422912597656,
            "box": [
                371,
                201,
                410,
                262
            ]
        },
        {
            "label": "bottle",
            "score": 0.8449215292930603,
            "box": [
                192,
                254,
                247,
                349
            ]
        },
        {
            "label": "table",
            "score": 0.700894832611084,
            "box": [
                0,
                97,
                562,
                462
            ]
        },
        {
            "label": "table",
            "score": 0.308190256357193,
            "box": [
                477,
                129,
                639,
                409
            ]
        }
    ]
}